flask_passwordless-0.1.0.dist-info/DESCRIPTION.rst
flask_passwordless-0.1.0.dist-info/top_level.txt
flask_passwordless-0.1.0.dist-info/WHEEL
flask_passwordless-0.1.0.dist-info/METADATA
flask_passwordless-0.1.0.dist-info/pydist.json
flask_passwordless-0.1.0.dist-info/RECORD
flask_passwordless/__init__.py
flask_passwordless/login_url.py
flask_passwordless/token_store.py
flask_passwordless/delivery_method.py
flask_passwordless/passwordless.py
