Metadata-Version: 2.0
Name: flask-passwordless
Version: 0.1.0
Summary: Flask extension for passwordless login
Home-page: https://github.com/kevinjqiu/flask-passwordless
Author: Kevin Qiu
Author-email: kevin@idempotent.ca
License: BSD
Keywords: flask,flask_passwordless
Platform: UNKNOWN
Classifier: Development Status :: 2 - Pre-Alpha
Classifier: Intended Audience :: Developers
Classifier: License :: OSI Approved :: BSD License
Classifier: Natural Language :: English
Classifier: Programming Language :: Python :: 2
Classifier: Programming Language :: Python :: 2.6
Classifier: Programming Language :: Python :: 2.7
Classifier: Programming Language :: Python :: 3
Classifier: Programming Language :: Python :: 3.3
